{
  "packageName": "All-in-One Presence Detection System",
  "author": "Luke Lee",
  "version": "0.7.0",
  "minimumHEVersion": "2.3.0",
  "dateReleased": "2026-04-26",
  "description": "All-in-One Presence Detection System - combines WiFi MQTT detection, GPS geofencing, Anyone logic, manual override, and delayed away. Includes individual presence drivers and composite aggregation driver for 'anyone home' functionality",
  "licenseFile": "https://raw.githubusercontent.com/zekaizer/hubitat-presense/main/LICENSE",
  "releaseNotes": "Version 0.7.0 - Migrated to homebridge-securitysystem v11.1.0+ API. Endpoints updated to PUT /mode/update and GET /state with Bearer authentication. Requires plugin v11.1.0 or later and API key configuration.",
  "documentationLink": "https://raw.githubusercontent.com/zekaizer/hubitat-presense/main/README.md",
  "communityLink": "https://community.hubitat.com/t/all-in-one-presence-detection-system/",
  "apps": [],
  "drivers": [
    {
      "id": "composite-presence",
      "name": "Composite Presence Driver",
      "namespace": "zekaizer",
      "location": "https://raw.githubusercontent.com/zekaizer/hubitat-presense/main/drivers/composite-presence-driver.groovy",
      "required": true,
      "primary": true
    },
    {
      "id": "all-in-one-presence",
      "name": "All-in-One Presence Driver",
      "namespace": "zekaizer",
      "location": "https://raw.githubusercontent.com/zekaizer/hubitat-presense/main/drivers/all-in-one-presence.groovy",
      "required": true,
      "primary": false
    }
  ],
  "tags": [
    "Presence",
    "WiFi",
    "GPS",
    "MQTT",
    "Geofencing",
    "Automation",
    "All-in-One",
    "Composite",
    "Aggregation"
  ],
  "category": "Convenience"
}